fsleyes_widgets/__init__.py
fsleyes_widgets/autotextctrl.py
fsleyes_widgets/bitmapradio.py
fsleyes_widgets/bitmaptoggle.py
fsleyes_widgets/colourbutton.py
fsleyes_widgets/dialog.py
fsleyes_widgets/elistbox.py
fsleyes_widgets/floatslider.py
fsleyes_widgets/floatspin.py
fsleyes_widgets/imagepanel.py
fsleyes_widgets/notebook.py
fsleyes_widgets/numberdialog.py
fsleyes_widgets/placeholder_textctrl.py
fsleyes_widgets/rangeslider.py
fsleyes_widgets/textpanel.py
fsleyes_widgets/texttag.py
fsleyes_widgets/togglepanel.py
fsleyes_widgets/widgetgrid.py
fsleyes_widgets/widgetlist.py
fsleyes_widgets/tests/__init__.py
fsleyes_widgets/tests/test_autotextctrl.py
fsleyes_widgets/tests/test_bitmapradio.py
fsleyes_widgets/tests/test_bitmaptoggle.py
fsleyes_widgets/tests/test_colourbarbitmap.py
fsleyes_widgets/tests/test_colourbutton.py
fsleyes_widgets/tests/test_elistbox.py
fsleyes_widgets/tests/test_floatslider.py
fsleyes_widgets/tests/test_floatspin.py
fsleyes_widgets/tests/test_imagepanel.py
fsleyes_widgets/tests/test_importall.py
fsleyes_widgets/tests/test_layout.py
fsleyes_widgets/tests/test_notebook.py
fsleyes_widgets/tests/test_numberdialog.py
fsleyes_widgets/tests/test_overlay.py
fsleyes_widgets/tests/test_placeholder_textctrl.py
fsleyes_widgets/tests/test_progress.py
fsleyes_widgets/tests/test_rangeslider.py
fsleyes_widgets/tests/test_runwindow.py
fsleyes_widgets/tests/test_status.py
fsleyes_widgets/tests/test_textbitmap.py
fsleyes_widgets/tests/test_textpanel.py
fsleyes_widgets/tests/test_texttag.py
fsleyes_widgets/tests/test_togglepanel.py
fsleyes_widgets/tests/test_typedict.py
fsleyes_widgets/tests/test_utils.py
fsleyes_widgets/tests/test_webpage.py
fsleyes_widgets/tests/test_widgetgrid.py
fsleyes_widgets/tests/testdata/bitmapbuttons/false.png
fsleyes_widgets/tests/testdata/bitmapbuttons/true.png
fsleyes_widgets/tests/testdata/colourbarbitmap/gamma_0.5_False_Greys_Greys.png
fsleyes_widgets/tests/testdata/colourbarbitmap/gamma_0.5_False_Greys_None.png
fsleyes_widgets-0.16.0.dist-info/licenses/LICENSE
fsleyes_widgets-0.16.0.dist-info/METADATA
fsleyes_widgets-0.16.0.dist-info/WHEEL
fsleyes_widgets-0.16.0.dist-info/top_level.txt
fsleyes_widgets-0.16.0.dist-info/RECORD
