Metadata-Version: 2.4
Name: fsleyes-widgets
Version: 0.16.0
Summary: A collection of wxPython widgets used by FSLeyes
Author-email: Paul McCarthy <pauldmccarthy@gmail.com>
Project-URL: Repository, https://git.fmrib.ox.ac.uk/fsl/fsleyes/widgets
Project-URL: Documentation, https://open.win.ox.ac.uk/pages/fsl/fsleyes/widgets/
Requires-Python: >=3.8
License-File: LICENSE
Requires-Dist: numpy
Requires-Dist: matplotlib>=3.5
Requires-Dist: wxPython>=3.0.2.0
Provides-Extra: doc
Requires-Dist: sphinx; extra == "doc"
Requires-Dist: sphinx_rtd_theme; extra == "doc"
Provides-Extra: test
Requires-Dist: pytest; extra == "test"
Requires-Dist: coverage; extra == "test"
Requires-Dist: pytest-cov; extra == "test"
Requires-Dist: tomli; python_version < "3.11" and extra == "test"
Provides-Extra: style
Requires-Dist: pylint; extra == "style"
Requires-Dist: flake8; extra == "style"
Dynamic: license-file
